doggy.py
doggy/__init__.py
doggy/doggy.py
doggy/file_operations.py
doggy/commands/__init__.py
doggy/commands/uc.py
doggy-1.0.2.dist-info/METADATA
doggy-1.0.2.dist-info/WHEEL
doggy-1.0.2.dist-info/entry_points.txt
doggy-1.0.2.dist-info/top_level.txt
doggy-1.0.2.dist-info/RECORD
